riscof/__init__.py
riscof/arch_test.py
riscof/cli.py
riscof/constants.py
riscof/dbgen.py
riscof/log.py
riscof/pluginTemplate.py
riscof/requirements.txt
riscof/utils.py
riscof/Templates/coverage.html
riscof/Templates/report.html
riscof/Templates/style.css
riscof/Templates/setup/config.ini
riscof/Templates/setup/model/model_isa.yaml
riscof/Templates/setup/model/model_platform.yaml
riscof/Templates/setup/model/riscof_model.py
riscof/Templates/setup/model/env/link.ld
riscof/Templates/setup/model/env/model_test.h
riscof/Templates/setup/reference/riscof_model.py
riscof/Templates/setup/reference/env/link.ld
riscof/Templates/setup/reference/env/model_test.h
riscof/Templates/setup/sail_cSim/__init__.py
riscof/Templates/setup/sail_cSim/riscof_sail_cSim.py
riscof/Templates/setup/sail_cSim/env/link.ld
riscof/Templates/setup/sail_cSim/env/model_test.h
riscof/framework/__init__.py
riscof/framework/main.py
riscof/framework/test.py
riscof-1.25.3.dist-info/LICENSE
riscof-1.25.3.dist-info/METADATA
riscof-1.25.3.dist-info/WHEEL
riscof-1.25.3.dist-info/entry_points.txt
riscof-1.25.3.dist-info/top_level.txt
riscof-1.25.3.dist-info/RECORD
