Metadata-Version: 1.2
Name: riscof
Version: 1.25.3
Summary: RISC-V Architectural Test Framework
Home-page: https://github.com/riscv/riscof
Author: InCore Semiconductors Pvt. Ltd.
Author-email: neelgala@incoresemi.com
License: BSD-3-Clause
Keywords: riscof
Platform: UNKNOWN
Classifier: Programming Language :: Python :: 3.6
Classifier: License :: OSI Approved :: BSD License
Classifier: Development Status :: 4 - Beta
Requires-Python: >=3.6.0
